virtualenvwrapper.djangodeploy-1.0.0-py2.7-nspkg.pth
virtualenvwrapper/django_deploy.py
virtualenvwrapper.djangodeploy-1.0.0.dist-info/DESCRIPTION.rst
virtualenvwrapper.djangodeploy-1.0.0.dist-info/entry_points.txt
virtualenvwrapper.djangodeploy-1.0.0.dist-info/METADATA
virtualenvwrapper.djangodeploy-1.0.0.dist-info/metadata.json
virtualenvwrapper.djangodeploy-1.0.0.dist-info/namespace_packages.txt
virtualenvwrapper.djangodeploy-1.0.0.dist-info/pbr.json
virtualenvwrapper.djangodeploy-1.0.0.dist-info/RECORD
virtualenvwrapper.djangodeploy-1.0.0.dist-info/top_level.txt
virtualenvwrapper.djangodeploy-1.0.0.dist-info/WHEEL
