Metadata-Version: 2.0
Name: virtualenvwrapper.djangodeploy
Version: 1.0.0
Summary: virtualenvwrapper plugin to create a Django deploy work directory
Home-page: https://github.com/tino/virtualenvwrapper.djangodeploy
Author: Tino de Bruijn
Author-email: tinodb@gmail.com
License: UNKNOWN
Platform: Any
Classifier: Development Status :: 3 - Alpha
Classifier: License :: OSI Approved :: BSD License
Classifier: Intended Audience :: Developers
Classifier: Environment :: Console
Classifier: Framework :: Django
Classifier: Programming Language :: Python :: 2
Classifier: Programming Language :: Python :: 2.6
Classifier: Programming Language :: Python :: 2.7
Classifier: Programming Language :: Python :: 3
Classifier: Programming Language :: Python :: 3.2
Classifier: Programming Language :: Python :: 3.3
Classifier: Programming Language :: Python :: 3.4
Requires: virtualenv
Requires: virtualenvwrapper (>=4.0)
Provides: virtualenvwrapper.djangodeploy
